drf_apitests/__init__.py
drf_apitests/apitest.py
drf_apitests/client.py
drf_apitests/exception.py
drf_apitests/metaclass.py
drf_apitests/runner.py
drf_apitests-0.1a4.dist-info/DESCRIPTION.rst
drf_apitests-0.1a4.dist-info/METADATA
drf_apitests-0.1a4.dist-info/RECORD
drf_apitests-0.1a4.dist-info/WHEEL
drf_apitests-0.1a4.dist-info/metadata.json
drf_apitests-0.1a4.dist-info/top_level.txt
