Metadata-Version: 2.0
Name: drf-apitests
Version: 0.1a4
Summary: API testing tools for Django REST Framework
Home-page: https://github.com/hjalves/drf-apitests
Author: Humberto Alves
Author-email: hjalves@live.com
License: MIT
Keywords: drf api testing
Platform: UNKNOWN
Classifier: Development Status :: 2 - Pre-Alpha
Classifier: Environment :: Console
Classifier: Intended Audience :: Developers
Classifier: Operating System :: POSIX :: Linux
Classifier: Programming Language :: Python :: 3
Classifier: Programming Language :: Python :: 3.6
Requires-Dist: Django (>=1.9)
Requires-Dist: djangorestframework
Requires-Dist: djangorestframework-jwt
Requires-Dist: PyYAML
